{
    "title": "Борис Ячев: Плоският данък да стане 9%",
    "timestamp": "28 май 2024  18:00",
    "content": "„Плоският данък да стане 9%, за ДДС да има тенденция за намаляване на 19 и на 18%”. Това заяви Борис Ячев, председател на партия „Консервативна България” и участник от листата на „Синя България” в предаването „Денят на живо” по NOVA NEWS. Той се надява тези данъчни промени да бъдат реализирани след изборите, ако представляваната от него формация влезе в 50-ото Народно събрание. Заплати, пенсии и данъци: Какво обещават кандидат-депутатите Като цел на своята политика той обясни, че повишаването на доходите може да стане само когато държавата се освободи от несвойствената си роля на търговец, брокер и на предприемач. Не изпускайте ритъма на деня! Последвайте ни в Google News Showcase",
    "translation": "The flat tax to become 9%, for VAT to have a tendency to decrease to 19 and 18%. This is what Boris Yachev, president of the party - Conservative Bulgaria and participant from the list of .Siny Bulgaria. He hopes that these tax changes will be implemented after the elections if the formation he represents enters the 50th National Assembly. Pay, pensions and taxes: What do the candidates promise as a goal of his policy he explained that the increase of income can only be made when the state is free of its unprivileged role as a trader, broker and entrepreneur. Don't miss the rhythm of the day! Follow us at Google News Showcase.",
    "detected_language": "bg",
    "transformed_representation": [
        "Finance",
        "tax reform",
        "Bulgaria",
        "elections",
        "politics",
        "Conservative Party",
        "Society"
    ]
}