{"id": 1217, "title": "„La vie en rose” – концерт-спектакъл посветен на Едит Пиаф (ВИДЕО)", "timestamp": "05 юни 2024  22:00", "content": "13-ото издание на Международния франкофонски фестивал „Солей” беше открито с концерт-спектакъл посветен на Едит Пиаф. Програмата е богата и включва международен пленер с художници от 8 държави, изложби, концерти, научни конференции и кино събития. Откриха Международния Франкофонски фестивал „Солей” (ВИДЕО) Повече гледайте във видеото. Новините от друг ъгъл - последвай ни в TikTok и открий лицата зад събитията, които формират света ни!", "keywords": ["Festivals", "Francophonie", "Culture", "Music", "Art", "Entertainment", "Cinéma"], "language": "bg", "translation": "The 13th edition of the International Francophone Festival was opened with a performance concert dedicated to Edith Piaf. The program is rich and includes an international plenipotentiary with artists from 8 countries, exhibitions, concerts, scientific conferences and cinema events. They opened the International Francophone Festival"}