{"id": 827, "title": "Михаил Константинов: Значението на ДПС сега е по-силно, отколкото преди години", "timestamp": "03 юли 2024  11:47", "content": "„Целият свят е в объркано състояние, сякаш всичко рухва изведнъж. България не прави изключение”. Това каза математикът проф. Михаил Константинов предаването „Твоят ден” по NOVA NEWS. Ние сме бегло отражение на световните процеси, допълни той. Според него разколът в ДПС е тежък. Значението на партията сега е по-силно, отколкото преди години, заради състоянието на света, смята бившият зам.-председател на ЦИК. ДПС изключи Рамадан Аталай от парламентарната група Според Слави Василев т.нар. „разпад” е нов хоризонт. „Вятърът на промяната”, който духа в Западния Свят довя и в България. Процесите в ДПС са вътрешнополитически, но това е промяна към едно по-светло бъдеще, смята той. Може би тези процеси там са необходимост, за да се промени българския политически живот. Целия разговор гледайте във видеото. Не изпускайте ритъма на деня! Последвайте ни в Google News Showcase", "keywords": ["Bulgaria", "politics", "news", "DPS", "Ramadan Atalay", "Slavi Vasilev"], "language": "bg", "translation": "The whole world is in a messed-up state, as if everything collapses suddenly. Bulgaria does not make an exception. This is what the mathematician Prof. Mikhail Konstantinov said. Your day is on NOVA NEWS. We are a slight reflection of the world processes, he added.The importance of the party is now stronger than it was years ago because of the state of the world, says the former Vice-President of the CEC. The DPS excluded Ramadan Atalay from the parliamentary group According to Slavi Vasilev, the so-called breakup is a new horizon.The processes in the DPS are internal political, but this is a change to a brighter future, he believes. Perhaps these processes there are necessary to change Bulgarian political life. The entire conversation look at the video. Don't miss the rhythm of the day! Follow us at Google News Showcase."}