{"id": 958, "title": "В кои градове по света разходите за живот са най-високи", "timestamp": "24 юни 2024  18:10", "content": "Най-големите финансови центрове в Азия отново завоюваха първите места като най-скъпите градове за живеене на хора, напуснали родината си, пише CNBC. Хонконг оглави класацията Cost of Living City Ranking 2024 година на Mercer, като след него се нареждат Сингапур и 4 града в Швейцария – Цюрих, Женева, Базел и Берн. Топ 10 допълват Ню Йорк, Лондон, Насау и Лос Анджелис. Българската столица София също е в класацията, но на 162-ра позицията. Проучването сравнява разходите за повече от 200 артикула във всеки от 226-те изследвани града, включително цените на жилищата, транспорта, храната, дрехите, домакинските стоки и развлеченията. Повече гледайте във видеото. Не изпускайте ритъма на деня! Последвайте ни в Google News Showcase", "keywords": ["Finance", "Asia", "Hong Kong", "Singapore", "Switzerland", "Cost of Living", "Mercer", "City Ranking", "New York", "London", "Los Angeles", "Nassau", "Sofia"], "language": "bg", "translation": "The largest financial centers in Asia once again won the first places as the most expensive cities for living people leaving their homeland, writes CNBC. Hong Kong topped the Cost of Living City Ranking 2024 by Mercer, after which are ranked Singapore and 4 cities in Switzerland Zürich, Geneva, Basel and Bern. Top 10 complement New York, London, Nassau and Los Angeles. The Bulgarian capital Sofia is also in the ranking, but on 162nd position. The study compares the costs for more than 200 items in each of 226 surveyed cities, including housing prices, transport, food, clothing, household goods and entertainment.More look in the video. Do not miss the beat of the day! Follow us on Google News Showcase."}